dispatchery/__init__.py
dispatchery/main.py
dispatchery-0.3.2.dist-info/LICENSE
dispatchery-0.3.2.dist-info/METADATA
dispatchery-0.3.2.dist-info/WHEEL
dispatchery-0.3.2.dist-info/top_level.txt
dispatchery-0.3.2.dist-info/RECORD
