Metadata-Version: 2.1
Name: dispatchery
Version: 0.3.2
Summary: A Python package for advanced function dispatching based on complex, nested, and parameterized types. Inspired by singledispatch.
Home-page: https://github.com/bolaft/dispatchery
Author: Soufian Salim
Author-email: soufian.salim@gmail.com
Keywords: dispatch,type-safety,singledispatch,functools,typing,types
Classifier: Intended Audience :: Developers
Classifier: Programming Language :: Python :: 3
Classifier: Programming Language :: Python :: 3.7
Classifier: Programming Language :: Python :: 3.8
Classifier: Programming Language :: Python :: 3.9
Classifier: Programming Language :: Python :: 3.10
Classifier: License :: OSI Approved :: MIT License
Classifier: Operating System :: OS Independent
Classifier: Topic :: Software Development :: Libraries :: Python Modules
Requires-Python: >=3.7
License-File: LICENSE
